proscenium/__init__.py
proscenium/complete.py
proscenium/history.py
proscenium/admin/__init__.py
proscenium/bin/__init__.py
proscenium/bin/bot.py
proscenium/interfaces/__init__.py
proscenium/interfaces/slack.py
proscenium/patterns/__init__.py
proscenium/patterns/graph_rag.py
proscenium/patterns/rag.py
proscenium/patterns/tools.py
proscenium/util/__init__.py
proscenium-0.0.14.dist-info/licenses/LICENSE
proscenium-0.0.14.dist-info/METADATA
proscenium-0.0.14.dist-info/WHEEL
proscenium-0.0.14.dist-info/entry_points.txt
proscenium-0.0.14.dist-info/top_level.txt
proscenium-0.0.14.dist-info/RECORD
