Metadata-Version: 2.4
Name: proscenium
Version: 0.0.14
Summary: Declare Collaborative, Asynchronous Human To Agent Interactions
Author-email: Adam Pingel <oss@pingel.org>
License-Expression: Apache-2.0
Requires-Python: >=3.11
License-File: LICENSE
Requires-Dist: aisuite>=0.1.10
Requires-Dist: docstring_parser>=0.16
Requires-Dist: pydantic>=2.10.6
Requires-Dist: rich>=13.9.4
Requires-Dist: slack_sdk>=3.35.0
Provides-Extra: test
Requires-Dist: pytest<9,>=8; extra == "test"
Requires-Dist: pytest-cov<6,>=5; extra == "test"
Requires-Dist: typer>=0.15.2; extra == "test"
Requires-Dist: click>=8.2.0; extra == "test"
Requires-Dist: pytest>=8.3.5; extra == "test"
Requires-Dist: neo4j>=5.28.1; extra == "test"
Requires-Dist: gofannon>=0.25.13; extra == "test"
Requires-Dist: lapidarist>=0.0.4; extra == "test"
Dynamic: license-file
